vecmbreak/__init__.py
vecmbreak/backward_elimination.py
vecmbreak/data_generation.py
vecmbreak/group_lasso.py
vecmbreak/inference.py
vecmbreak/irf.py
vecmbreak/output.py
vecmbreak/principal_component.py
vecmbreak/py.typed
vecmbreak/utils.py
vecmbreak/vecm_break.py
vecmbreak/tests/__init__.py
vecmbreak/tests/test_vecmbreak.py
vecmbreak-0.1.1.dist-info/licenses/LICENSE
vecmbreak-0.1.1.dist-info/METADATA
vecmbreak-0.1.1.dist-info/WHEEL
vecmbreak-0.1.1.dist-info/top_level.txt
vecmbreak-0.1.1.dist-info/RECORD
