Metadata-Version: 2.4
Name: vecmbreak
Version: 0.1.1
Summary: Multiple Structural Break Detection in Vector Error Correction Models
Author-email: "Franjic, Mößler, Schweikert" <vecmbreak@example.com>
Maintainer-email: "Franjic, Mößler, Schweikert" <vecmbreak@example.com>
License-Expression: MIT
Project-URL: Homepage, https://github.com/vecmbreak/vecmbreak
Project-URL: Documentation, https://vecmbreak.readthedocs.io
Project-URL: Repository, https://github.com/vecmbreak/vecmbreak
Project-URL: Issues, https://github.com/vecmbreak/vecmbreak/issues
Project-URL: Changelog, https://github.com/vecmbreak/vecmbreak/blob/main/CHANGELOG.md
Keywords: econometrics,VECM,vector error correction model,structural breaks,cointegration,time series,group lasso,backward elimination,principal components
Classifier: Development Status :: 4 - Beta
Classifier: Intended Audience :: Science/Research
Classifier: Intended Audience :: Financial and Insurance Industry
Classifier: Operating System :: OS Independent
Classifier: Programming Language :: Python :: 3
Classifier: Programming Language :: Python :: 3.9
Classifier: Programming Language :: Python :: 3.10
Classifier: Programming Language :: Python :: 3.11
Classifier: Programming Language :: Python :: 3.12
Classifier: Topic :: Scientific/Engineering :: Mathematics
Classifier: Topic :: Scientific/Engineering :: Information Analysis
Classifier: Topic :: Office/Business :: Financial :: Investment
Requires-Python: >=3.9
License-File: LICENSE
Requires-Dist: numpy>=1.20.0
Requires-Dist: scipy>=1.7.0
Requires-Dist: statsmodels>=0.13.0
Requires-Dist: patsy>=0.5.0
Provides-Extra: dev
Requires-Dist: pytest>=7.0.0; extra == "dev"
Requires-Dist: pytest-cov>=4.0.0; extra == "dev"
Requires-Dist: black>=23.0.0; extra == "dev"
Requires-Dist: isort>=5.12.0; extra == "dev"
Requires-Dist: flake8>=6.0.0; extra == "dev"
Requires-Dist: mypy>=1.0.0; extra == "dev"
Provides-Extra: docs
Requires-Dist: sphinx>=6.0.0; extra == "docs"
Requires-Dist: sphinx-rtd-theme>=1.2.0; extra == "docs"
Requires-Dist: numpydoc>=1.5.0; extra == "docs"
Provides-Extra: plotting
Requires-Dist: matplotlib>=3.5.0; extra == "plotting"
Requires-Dist: pandas>=1.4.0; extra == "plotting"
Provides-Extra: full
Requires-Dist: matplotlib>=3.5.0; extra == "full"
Requires-Dist: pandas>=1.4.0; extra == "full"
Dynamic: license-file
